Workbook

Sheet Room Directory
A1: 🏨 MARUYOG RIDGE — ROOM DIRECTORY
A2: Maruyog Ridge Mountain Resort & Spa · Bukidnon, Philippines · As of 2025–2026
A3: Room No. | B3: Floor | C3: Room Type | D3: Bed Config. | E3: Max Pax | F3: View | G3: Weekday Rate (₱) | H3: Weekend Rate (₱) | I3: Peak Rate (₱) | J3: Amenities | K3: Size (sqm) | L3: Smoking | M3: Status | N3: Notes
A4: 101 | B4: 1 | C4: Standard Room | D4: 1 Queen Bed | E4: 2 | F4: Garden View | G4: 2500 | H4: 3000 | I4: 3500 | J4: AC, TV, WiFi, Private Bath, Balcony | K4: 24 | L4: No | M4: ✅ Available | N4: Ground floor garden access
A5: 102 | B5: 1 | C5: Standard Room | D5: 1 Queen Bed | E5: 2 | F5: Garden View | G5: 2500 | H5: 3000 | I5: 3500 | J5: AC, TV, WiFi, Private Bath, Balcony | K5: 24 | L5: No | M5: ✅ Available
A6: 103 | B6: 1 | C6: Standard Room | D6: 2 Single Beds | E6: 3 | F6: Garden View | G6: 2800 | H6: 3200 | I6: 3800 | J6: AC, TV, WiFi, Private Bath | K6: 26 | L6: No | M6: 🔧 Maintenance | N6: Aircon repair scheduled
A7: 104 | B7: 1 | C7: Standard Room | D7: 1 Queen Bed | E7: 2 | F7: Pool View | G7: 2800 | H7: 3300 | I7: 3800 | J7: AC, TV, WiFi, Private Bath, Balcony | K7: 25 | L7: No | M7: ✅ Available
A8: 105 | B8: 1 | C8: Deluxe Room | D8: 1 King Bed | E8: 2 | F8: Mountain View | G8: 3800 | H8: 4500 | I8: 5200 | J8: AC, Smart TV, WiFi, Mini-bar, Bathtub, Balcony | K8: 32 | L8: No | M8: 🛏 Occupied
A9: 106 | B9: 1 | C9: Deluxe Room | D9: 1 King Bed | E9: 2 | F9: Mountain View | G9: 3800 | H9: 4500 | I9: 5200 | J9: AC, Smart TV, WiFi, Mini-bar, Bathtub, Balcony | K9: 32 | L9: No | M9: ✅ Available
A10: 107 | B10: 1 | C10: Family Room | D10: 2 Queen Beds | E10: 4 | F10: Garden View | G10: 4500 | H10: 5200 | I10: 6000 | J10: AC, Smart TV, WiFi, Mini-bar, 2 Baths, Living Area | K10: 45 | L10: No | M10: 🛏 Occupied
A11: 108 | B11: 1 | C11: Family Room | D11: 2 Queen Beds | E11: 4 | F11: Pool View | G11: 4800 | H11: 5500 | I11: 6500 | J11: AC, Smart TV, WiFi, Mini-bar, 2 Baths, Living Area | K11: 48 | L11: No | M11: ✅ Available
A12: 201 | B12: 2 | C12: Standard Room | D12: 1 Queen Bed | E12: 2 | F12: Mountain View | G12: 2800 | H12: 3300 | I12: 3800 | J12: AC, TV, WiFi, Private Bath, Balcony | K12: 24 | L12: No | M12: ✅ Available
A13: 202 | B13: 2 | C13: Standard Room | D13: 2 Single Beds | E13: 3 | F13: Mountain View | G13: 2800 | H13: 3300 | I13: 3800 | J13: AC, TV, WiFi, Private Bath | K13: 26 | L13: No | M13: ✅ Available
A14: 203 | B14: 2 | C14: Deluxe Room | D14: 1 King Bed | E14: 2 | F14: Mountain View | G14: 4000 | H14: 4800 | I14: 5500 | J14: AC, Smart TV, WiFi, Mini-bar, Bathtub, Balcony | K14: 33 | L14: No | M14: 🛏 Occupied
A15: 204 | B15: 2 | C15: Deluxe Room | D15: 1 King Bed | E15: 2 | F15: Valley View | G15: 4000 | H15: 4800 | I15: 5500 | J15: AC, Smart TV, WiFi, Mini-bar, Bathtub, Balcony | K15: 33 | L15: No | M15: ✅ Available
A16: 205 | B16: 2 | C16: Deluxe Room | D16: 2 Double Beds | E16: 4 | F16: Valley View | G16: 4500 | H16: 5200 | I16: 6000 | J16: AC, Smart TV, WiFi, Mini-bar, Bathtub, Balcony | K16: 36 | L16: No | M16: ✅ Available
A17: 206 | B17: 2 | C17: Junior Suite | D17: 1 King Bed | E17: 2 | F17: Mountain View | G17: 6500 | H17: 7500 | I17: 9000 | J17: AC, Smart TV, WiFi, Mini-bar, Jacuzzi, Sala Set, Balcony | K17: 52 | L17: No | M17: 🛏 Occupied
A18: 207 | B18: 2 | C18: Junior Suite | D18: 1 King Bed | E18: 2 | F18: Valley View | G18: 6500 | H18: 7500 | I18: 9000 | J18: AC, Smart TV, WiFi, Mini-bar, Jacuzzi, Sala Set, Balcony | K18: 52 | L18: No | M18: ✅ Available
A19: 208 | B19: 2 | C19: Family Room | D19: 2 Queen Beds | E19: 5 | F19: Mountain View | G19: 5000 | H19: 5800 | I19: 7000 | J19: AC, Smart TV, WiFi, Mini-bar, 2 Baths, Kids Area, Balcony | K19: 55 | L19: No | M19: ✅ Available
A20: 301 | B20: 3 | C20: Deluxe Room | D20: 1 King Bed | E20: 2 | F20: Mountain View | G20: 4200 | H20: 5000 | I20: 5800 | J20: AC, Smart TV, WiFi, Mini-bar, Bathtub, Balcony | K20: 34 | L20: No | M20: ✅ Available | N20: High floor, best view
A21: 302 | B21: 3 | C21: Deluxe Room | D21: 1 King Bed | E21: 2 | F21: 360° View | G21: 4500 | H21: 5200 | I21: 6200 | J21: AC, Smart TV, WiFi, Mini-bar, Bathtub, Panoramic Balcony | K21: 36 | L21: No | M21: 🛏 Occupied
A22: 303 | B22: 3 | C22: Junior Suite | D22: 1 King Bed | E22: 2 | F22: 360° View | G22: 7000 | H22: 8000 | I22: 9500 | J22: AC, Smart TV, WiFi, Mini-bar, Jacuzzi, Sala Set, Balcony | K22: 55 | L22: No | M22: ✅ Available
A23: 304 | B23: 3 | C23: Junior Suite | D23: 1 King Bed + Sofa | E23: 3 | F23: Mountain View | G23: 7200 | H23: 8200 | I23: 9800 | J23: AC, Smart TV, WiFi, Mini-bar, Jacuzzi, Sala Set, Balcony | K23: 58 | L23: No | M23: 🛏 Occupied | N23: VIP guest
A24: 305 | B24: 3 | C24: Executive Suite | D24: 1 King Bed | E24: 2 | F24: 360° View | G24: 10500 | H24: 12000 | I24: 15000 | J24: AC, Smart TV, WiFi, Full Bar, Jacuzzi, Dining Area, 2 Balconies | K24: 80 | L24: No | M24: ✅ Available
A25: 306 | B25: 3 | C25: Executive Suite | D25: 1 King Bed | E25: 2 | F25: Mountain View | G25: 10000 | H25: 11500 | I25: 14000 | J25: AC, Smart TV, WiFi, Full Bar, Jacuzzi, Dining Area, Balcony | K25: 78 | L25: No | M25: 🔧 Maintenance | N25: Plumbing works
A26: 307 | B26: 3 | C26: Presidential Suite | D26: 1 King + 2 Singles | E26: 6 | F26: 360° View | G26: 18000 | H26: 22000 | I26: 28000 | J26: AC, Smart TV, WiFi, Full Bar, Private Pool, Jacuzzi, Kitchen, Dining, 3 Balconies | K26: 150 | L26: No | M26: ✅ Available | N26: Top-floor centerpiece
A27: C01 | B27: G | C27: Cottage | D27: 2 Queen Beds | E27: 4 | F27: Forest View | G27: 5500 | H27: 6500 | I27: 8000 | J27: Fan/AC, TV, WiFi, Private Bath, Veranda, BBQ Area | K27: 40 | L27: No | M27: ✅ Available | N27: Private cottage
A28: C02 | B28: G | C28: Cottage | D28: 2 Queen Beds | E28: 4 | F28: Forest View | G28: 5500 | H28: 6500 | I28: 8000 | J28: Fan/AC, TV, WiFi, Private Bath, Veranda, BBQ Area | K28: 40 | L28: No | M28: 🛏 Occupied
A29: C03 | B29: G | C29: Cottage | D29: 1 King + 2 Singles | E29: 6 | F29: Garden View | G29: 7000 | H29: 8500 | I29: 10000 | J29: AC, Smart TV, WiFi, 2 Private Baths, Veranda, BBQ, Outdoor Shower | K29: 55 | L29: No | M29: ✅ Available | N29: Family cottage
A30: C04 | B30: G | C30: Glamping Tent | D30: 2 Single Beds | E30: 2 | F30: Forest View | G30: 1800 | H30: 2200 | I30: 2800 | J30: Fan, WiFi, Shared Bath, Veranda | K30: 18 | L30: No | M30: ✅ Available | N30: Eco-friendly option
A31: C05 | B31: G | C31: Glamping Tent | D31: 1 Queen Bed | E31: 2 | F31: Mountain View | G31: 2000 | H31: 2500 | I31: 3200 | J31: Fan, WiFi, Shared Bath, Veranda | K31: 20 | L31: No | M31: ✅ Available
A32: C06 | B32: G | C32: Glamping Tent | D32: 2 Single Beds | E32: 2 | F32: Forest View | G32: 1800 | H32: 2200 | I32: 2800 | J32: Fan, WiFi, Shared Bath, Veranda | K32: 18 | L32: No | M32: 🚫 Closed | N32: Off-season closure
A33: D01 | B33: G | C33: Dormitory | D33: 8 Bunk Beds | E33: 8 | F33: Garden View | G33: 600 | H33: 700 | I33: 900 | J33: Fan, WiFi, Shared Bath, Locker | K33: 65 | L33: No | M33: ✅ Available | N33: Per person rate
A34: D02 | B34: G | C34: Dormitory | D34: 10 Bunk Beds | E34: 10 | F34: Garden View | G34: 600 | H34: 700 | I34: 900 | J34: Fan, WiFi, Shared Bath, Locker | K34: 75 | L34: No | M34: ✅ Available | N34: Per person rate

Sheet Guest Master List
A1: 👥 MARUYOG RIDGE — GUEST MASTER LIST
A2: Registered Guests · 2025–2026 · Maruyog Ridge Mountain Resort & Spa
A3: Guest ID | B3: Last Name | C3: First Name | D3: Contact No. | E3: Email Address | F3: Nationality | G3: ID Type | H3: ID Number | I3: Address | J3: Birthday | K3: VIP Status | L3: Total Stays | M3: Total Spent (₱)
A4: G-001 | B4: Reyes | C4: Maria Clara | D4: *********** | E4: ************************ | F4: Filipino | G4: UMID | H4: *********** | I4: 123 Rizal St., Cagayan de Oro City | J4: 32217 | K4: ⭐ VIP | L4: 8 | M4: 85000
A5: G-002 | B5: Santos | C5: Jose Antonio | D5: *********** | E5: ************************ | F5: Filipino | G5: Driver's License | H5: *********** | I5: 456 Mabini Ave., Iligan City | J5: 27597 | K5: Regular | L5: 3 | M5: 24000
A6: G-003 | B6: Tan | C6: Michelle | D6: *********** | E6: ************************ | F6: Filipino | G6: Passport | H6: *********** | I6: 789 Quezon Blvd., Manila | J6: 33916 | K6: ⭐ VIP | L6: 12 | M6: 156000
A7: G-004 | B7: Lim | C7: Patrick John | D7: *********** | E7: ************************ | F7: Filipino | G7: PhilSys | H7: *********** | I7: 23 Osmena St., Davao City | J7: 31228 | K7: Regular | L7: 2 | M7: 18500
A8: G-005 | B8: Garcia | C8: Anna Marie | D8: *********** | E8: ************************ | F8: Filipino | G8: UMID | H8: *********** | I8: 78 Bonifacio St., Bukidnon | J8: 33128 | K8: Regular | L8: 5 | M8: 41000
A9: G-006 | B9: Kim | C9: Jisoo | D9: *********** | E9: ************************ | F9: Korean | G9: Passport | H9: *********** | I9: Seoul, South Korea | J9: 34702 | K9: Regular | L9: 1 | M9: 22000
A10: G-007 | B10: Nguyen | C10: Tran Minh | D10: *********** | E10: ************************ | F10: Vietnamese | G10: Passport | H10: *********** | I10: Ho Chi Minh City, Vietnam | J10: 32251 | K10: Regular | L10: 1 | M10: 15000
A11: G-008 | B11: Cruz | C11: Roberto | D11: *********** | E11: ************************ | F11: Filipino | G11: Driver's License | H11: *********** | I11: 101 Aguinaldo St., Cebu City | J11: 28829 | K11: ⭐⭐ Diamond | L11: 22 | M11: 385000
A12: G-009 | B12: Fernandez | C12: Sophia Grace | D12: *********** | E12: ************************ | F12: Filipino | G12: Passport | H12: *********** | I12: 34 Magsaysay Ave., Zamboanga | J12: 34208 | K12: Regular | L12: 2 | M12: 19000
A13: G-010 | B13: Manalo | C13: Benedict | D13: *********** | E13: ************************ | F13: Filipino | G13: UMID | H13: *********** | I13: 56 Commonwealth Ave., QC | J13: 29265 | K13: ⭐ VIP | L13: 9 | M13: 120000
A14: G-011 | B14: Smith | C14: Robert James | D14: *********** | E14: ************************ | F14: American | G14: Passport | H14: *********** | I14: Los Angeles, California, USA | J14: 26439 | K14: Regular | L14: 2 | M14: 48000
A15: G-012 | B15: Aquino | C15: Carla Mae | D15: *********** | E15: ************************ | F15: Filipino | G15: PhilSys | H15: *********** | I15: 89 Roxas Blvd., Manila | J15: 35734 | K15: Regular | L15: 1 | M15: 12500
... A38: G-035 | B38: Reyes | C38: Juan Miguel | D38: *********** | E38: ************************ | F38: Filipino | G38: PhilSys | H38: *********** | I38: 33 Gaerlan St., Cagayan de Oro | J38: 34747 | K38: Regular | L38: 1 | M38: 9500

Sheet Booking Log
A1: 📋 MARUYOG RIDGE — BOOKING LOG 2025–2026
A2: Complete Reservation & Stay Records · Maruyog Ridge Mountain Resort & Spa
A3: Booking ID | B3: Guest ID | C3: Guest Name | D3: Room No. | E3: Room Type | F3: Check-In | G3: Check-Out | H3: Nights | I3: Pax | J3: Rate/Night (₱) | K3: Room Total (₱) | L3: Add-ons (₱) | M3: Discount (₱) | N3: Grand Total (₱) | O3: Paid (₱) | P3: Balance (₱) | Q3: Payment Method | R3: Status
A4: BK-2025-001 | B4: G-001 | C4: Reyes, Maria Clara | D4: 206 | E4: Junior Suite | F4: 45660 | G4: 45663 | H4: 3 | I4: 2 | J4: 6500 | K4: =J4*H4 -> 19500 | L4: 4300 | M4: 500 | N4: =K4+L4-M4 -> 23300 | O4: 23300 | P4: =N4-O4 -> 0 | Q4: GCash | R4: ✅ Checked Out
A5: BK-2025-002 | B5: G-008 | C5: Cruz, Roberto | D5: 307 | E5: Presidential Suite | F5: 45667 | G5: 45671 | H5: 4 | I5: 4 | J5: 18000 | K5: =J5*H5 -> 72000 | L5: 0 | M5: 3000 | N5: =K5+L5-M5 -> 69000 | O5: 55200 | P5: =N5-O5 -> 13800 | Q5: GCash | R5: ✅ Checked Out
A6: BK-2025-003 | B6: G-013 | C6: Ramos, Eduardo | D6: 305 | E6: Executive Suite | F6: 45672 | G6: 45675 | H6: 3 | I6: 2 | J6: 10500 | K6: =J6*H6 -> 31500 | L6: 1800 | M6: 0 | N6: =K6+L6-M6 -> 33300 | O6: 33300 | P6: =N6-O6 -> 0 | Q6: GCash | R6: ✅ Checked Out
A7: BK-2025-004 | B7: G-002 | C7: Santos, Jose Antonio | D7: 104 | E7: Standard Room | F7: 45677 | G7: 45679 | H7: 2 | I7: 2 | J7: 2800 | K7: =J7*H7 -> 5600 | L7: 0 | M7: 0 | N7: =K7+L7-M7 -> 5600 | O7: 5600 | P7: =N7-O7 -> 0 | Q7: Credit Card | R7: ✅ Checked Out
A8: BK-2025-005 | B8: G-011 | C8: Smith, Robert James | D8: 203 | E8: Deluxe Room | F8: 45682 | G8: 45686 | H8: 4 | I8: 2 | J8: 4000 | K8: =J8*H8 -> 16000 | L8: 3000 | M8: 500 | N8: =K8+L8-M8 -> 18500 | O8: 0 | P8: =N8-O8 -> 18500 | Q8: Credit Card | R8: ✅ Checked Out
A9: BK-2025-006 | B9: G-022 | C9: Torres, Rico Paolo | D9: 207 | E9: Junior Suite | F9: 45695 | G9: 45698 | H9: 3 | I9: 2 | J9: 7500 | K9: =J9*H9 -> 22500 | L9: 5000 | M9: 1000 | N9: =K9+L9-M9 -> 26500 | O9: 26500 | P9: =N9-O9 -> 0 | Q9: Maya | R9: ✅ Checked Out
A10: BK-2025-007 | B10: G-025 | C10: Domingo, Francis | D10: 307 | E10: Presidential Suite | F10: 45702 | G10: 45705 | H10: 3 | I10: 2 | J10: 22000 | K10: =J10*H10 -> 66000 | L10: 10000 | M10: 2000 | N10: =K10+L10-M10 -> 74000 | O10: 59200 | P10: =N10-O10 -> 14800 | Q10: Credit Card | R10: ✅ Checked Out
A11: BK-2025-008 | B11: G-003 | C11: Tan, Michelle | D11: 305 | E11: Executive Suite | F11: 45702 | G11: 45704 | H11: 2 | I11: 2 | J11: 12000 | K11: =J11*H11 -> 24000 | L11: 5000 | M11: 2500 | N11: =K11+L11-M11 -> 26500 | O11: 26500 | P11: =N11-O11 -> 0 | Q11: Corporate Account | R11: ✅ Checked Out
A12: BK-2025-009 | B12: G-010 | C12: Manalo, Benedict | D12: 206 | E12: Junior Suite | F12: 45708 | G12: 45711 | H12: 3 | I12: 2 | J12: 7500 | K12: =J12*H12 -> 22500 | L12: 1800 | M12: 500 | N12: =K12+L12-M12 -> 23800 | O12: 23800 | P12: =N12-O12 -> 0 | Q12: GCash | R12: ✅ Checked Out
A13: BK-2025-010 | B13: G-006 | C13: Kim, Jisoo | D13: 302 | E13: Deluxe Room | F13: 45710 | G13: 45714 | H13: 4 | I13: 2 | J13: 5200 | K13: =J13*H13 -> 20800 | L13: 3000 | M13: 0 | N13: =K13+L13-M13 -> 23800 | O13: 0 | P13: =N13-O13 -> 23800 | Q13: Credit Card | R13: ✅ Checked Out
A14: BK-2025-011 | B14: G-014 | C14: Park, Seungri | D14: C01 | E14: Cottage | F14: 45717 | G14: 45720 | H14: 3 | I14: 3 | J14: 5500 | K14: =J14*H14 -> 16500 | L14: 2500 | M14: 0 | N14: =K14+L14-M14 -> 19000 | O14: 9500 | P14: =N14-O14 -> 9500 | Q14: Bank Transfer | R14: ✅ Checked Out
A15: BK-2025-012 | B15: G-005 | C15: Garcia, Anna Marie | D15: 107 | E15: Family Room | F15: 45723 | G15: 45726 | H15: 3 | I15: 4 | J15: 4500 | K15: =J15*H15 -> 13500 | L15: 5400 | M15: 800 | N15: =K15+L15-M15 -> 18100 | O15: 18100 | P15: =N15-O15 -> 0 | Q15: GCash | R15: ✅ Checked Out
... A83: BK-2026-020 | B83: G-010 | C83: Manalo, Benedict | D83: 307 | E83: Presidential Suite | F83: 46171 | G83: 46174 | H83: 3 | I83: 3 | J83: 18000 | K83: =J83*H83 -> 54000 | L83: 12000 | M83: 3000 | N83: =K83+L83-M83 -> 63000 | O83: 63000 | P83: =N83-O83 -> 0 | Q83: Credit Card | R83: 📋 Confirmed

Sheet Housekeeping
A1: 🧹 MARUYOG RIDGE — HOUSEKEEPING & MAINTENANCE LOG
A2: Daily Room Status & Maintenance Tracking · Week of April 21, 2026
A3: Room No. | B3: Room Type | C3: Floor | D3: Cleaning Status | E3: Last Cleaned | F3: Cleaned By | G3: Inspection | H3: Inspected By | I3: Maintenance | J3: Remarks | K3: Priority | L3: Next Service
A4: 101 | B4: Standard Room | C4: 1 | D4: ✅ Clean | E4: 2026-04-23 | F4: Maria L. | G4: ✅ Passed | H4: Supervisor A | I4: None | J4: Ready for check-in | K4: Normal | L4: 2026-04-24
A5: 102 | B5: Standard Room | C5: 1 | D5: ✅ Clean | E5: 2026-04-23 | F5: Ana R. | G5: ✅ Passed | H5: Supervisor A | I5: None | K5: Normal | L5: 2026-04-24
A6: 103 | B6: Standard Room | C6: 1 | D6: 🔧 Maintenance | E6: 2026-04-22 | F6: Jose M. | G6: ⏳ Pending | H6: — | I6: Aircon repair | J6: Technician scheduled 10AM | K6: 🔴 High | L6: 2026-04-24
A7: 104 | B7: Standard Room | C7: 1 | D7: 🛏 Occupied | E7: 2026-04-22 | F7: Maria L. | G7: ✅ Passed | H7: Supervisor B | I7: None | J7: Guest extended stay | K7: Normal | L7: 2026-04-25
A8: 105 | B8: Deluxe Room | C8: 1 | D8: 🛏 Occupied | E8: 2026-04-21 | F8: Ana R. | G8: ✅ Passed | H8: Supervisor A | I8: None | J8: VIP - Do not disturb | K8: Normal | L8: 2026-04-25
A9: 106 | B9: Deluxe Room | C9: 1 | D9: ✅ Clean | E9: 2026-04-23 | F9: Rosa C. | G9: ✅ Passed | H9: Supervisor B | I9: None | J9: Deep cleaned | K9: Normal | L9: 2026-04-24
A10: 107 | B10: Family Room | C10: 1 | D10: 🛏 Occupied | E10: 2026-04-20 | F10: Maria L. | G10: ✅ Passed | H10: Supervisor A | I10: None | J10: Family — extra towels requested | K10: Normal | L10: 2026-04-24
A11: 108 | B11: Family Room | C11: 1 | D11: 🔄 Turnover | E11: 2026-04-23 | F11: Ana R. | G11: ⏳ Pending | H11: — | I11: None | J11: Checkout 11AM, check-in 2PM | K11: 🟡 Medium | L11: 2026-04-23
A12: 201 | B12: Standard Room | C12: 2 | D12: ✅ Clean | E12: 2026-04-23 | F12: Rosa C. | G12: ✅ Passed | H12: Supervisor B | I12: None | K12: Normal | L12: 2026-04-24
A13: 202 | B13: Standard Room | C13: 2 | D13: ✅ Clean | E13: 2026-04-23 | F13: Jose M. | G13: ✅ Passed | H13: Supervisor A | I13: None | K13: Normal | L13: 2026-04-24
A14: 203 | B14: Deluxe Room | C14: 2 | D14: 🛏 Occupied | E14: 2026-04-22 | F14: Maria L. | G14: ✅ Passed | H14: Supervisor B | I14: None | J14: Guest requested extra pillow | K14: Normal | L14: 2026-04-25
A15: 204 | B15: Deluxe Room | C15: 2 | D15: ✅ Clean | E15: 2026-04-23 | F15: Ana R. | G15: ✅ Passed | H15: Supervisor A | I15: None | K15: Normal | L15: 2026-04-24
A16: 205 | B16: Deluxe Room | C16: 2 | D16: ✅ Clean | E16: 2026-04-23 | F16: Rosa C. | G16: ✅ Passed | H16: Supervisor B | I16: None | K16: Normal | L16: 2026-04-24
A17: 206 | B17: Junior Suite | C17: 2 | D17: 🛏 Occupied | E17: 2026-04-21 | F17: Maria L. | G17: ✅ Passed | H17: Supervisor A | I17: None | J17: VIP — Amenity replenished | K17: Normal | L17: 2026-04-24
A18: 207 | B18: Junior Suite | C18: 2 | D18: ✅ Clean | E18: 2026-04-23 | F18: Jose M. | G18: ✅ Passed | H18: Supervisor B | I18: None | K18: Normal | L18: 2026-04-24
A19: 208 | B19: Family Room | C19: 2 | D19: ✅ Clean | E19: 2026-04-23 | F19: Ana R. | G19: ✅ Passed | H19: Supervisor A | I19: None | K19: Normal | L19: 2026-04-24
A20: 301 | B20: Deluxe Room | C20: 3 | D20: ✅ Clean | E20: 2026-04-23 | F20: Rosa C. | G20: ✅ Passed | H20: Supervisor B | I20: None | J20: High floor — panoramic view | K20: Normal | L20: 2026-04-24
A21: 302 | B21: Deluxe Room | C21: 3 | D21: 🛏 Occupied | E21: 2026-04-22 | F21: Maria L. | G21: ✅ Passed | H21: Supervisor A | I21: None | J21: Korean guest — slippers added | K21: Normal | L21: 2026-04-25
A22: 303 | B22: Junior Suite | C22: 3 | D22: ✅ Clean | E22: 2026-04-23 | F22: Jose M. | G22: ✅ Passed | H22: Supervisor B | I22: None | K22: Normal | L22: 2026-04-24
A23: 304 | B23: Junior Suite | C23: 3 | D23: 🛏 Occupied | E23: 2026-04-20 | F23: Ana R. | G23: ✅ Passed | H23: Supervisor A | I23: None | J23: VIP guest — do not disturb | K23: Normal | L23: 2026-04-26
A24: 305 | B24: Executive Suite | C24: 3 | D24: 🔧 Maintenance | E24: 2026-04-21 | F24: Rosa C. | G24: ⏳ Pending | H24: — | I24: Plumbing works | J24: Plumber scheduled today | K24: 🔴 High | L24: 2026-04-24
A25: 306 | B25: Executive Suite | C25: 3 | D25: 🔧 Maintenance | E25: 2026-04-20 | F25: Jose M. | G25: ⏳ Pending | H25: — | I25: Renovation | J25: Ongoing renovation works | K25: 🔴 High | L25: 2026-04-30
A26: 307 | B26: Presidential Suite | C26: 3 | D26: 🛏 Occupied | E26: 2026-04-19 | F26: Maria L. | G26: ✅ Passed | H26: Supervisor A | I26: None | J26: VVIP — Butler assigned | K26: Normal | L26: 2026-04-26
A27: C01 | B27: Cottage | C27: G | D27: ✅ Clean | E27: 2026-04-23 | F27: Ana R. | G27: ✅ Passed | H27: Supervisor B | I27: None | J27: Outdoor area swept | K27: Normal | L27: 2026-04-24
A28: C02 | B28: Cottage | C28: G | D28: 🛏 Occupied | E28: 2026-04-22 | F28: Rosa C. | G28: ✅ Passed | H28: Supervisor A | I28: None | J28: BBQ set up by guest | K28: Normal | L28: 2026-04-25
A29: C03 | B29: Cottage | C29: G | D29: 🔄 Turnover | E29: 2026-04-23 | F29: Jose M. | G29: ⏳ Pending | H29: — | I29: None | J29: Deep clean after 5-pax group | K29: 🟡 Medium | L29: 2026-04-23
A30: C04 | B30: Glamping Tent | C30: G | D30: ✅ Clean | E30: 2026-04-23 | F30: Ana R. | G30: ✅ Passed | H30: Supervisor B | I30: None | J30: Linens replaced | K30: Normal | L30: 2026-04-24
A31: C05 | B31: Glamping Tent | C31: G | D31: ✅ Clean | E31: 2026-04-23 | F31: Rosa C. | G31: ✅ Passed | H31: Supervisor A | I31: None | K31: Normal | L31: 2026-04-24
A32: C06 | B32: Glamping Tent | C32: G | D32: 🚫 Closed | E32: 2026-04-01 | F32: — | G32: — | H32: — | I32: Off-season | J32: Closed until June 2026 | K32: Normal | L32: 2026-06-01
A33: D01 | B33: Dormitory | C33: G | D33: ✅ Clean | E33: 2026-04-23 | F33: Jose M. | G33: ✅ Passed | H33: Supervisor B | I33: None | J33: All 8 lockers sanitized | K33: Normal | L33: 2026-04-24
A34: D02 | B34: Dormitory | C34: G | D34: ✅ Clean | E34: 2026-04-23 | F34: Maria L. | G34: ✅ Passed | H34: Supervisor A | I34: None | K34: Normal | L34: 2026-04-24

Sheet Revenue Dashboard
A1: 📊 MARUYOG RIDGE — REVENUE DASHBOARD 2025–2026
A2: Financial Performance Overview · Maruyog Ridge Mountain Resort & Spa · Generated: 2026-04-23
A4: TOTAL REVENUE 2025 | F4: TOTAL BOOKINGS | K4: OCCUPANCY RATE
A5: ₱3,842,500 | F5: 80 | K5: 78.4%
A6: All Collected Payments | F6: Reservations 2025–2026 | K6: Avg Monthly Occupancy
A8: 📅 MONTHLY PERFORMANCE — 2025 | I8: 🏨 REVENUE BY ROOM TYPE
A9: Month | B9: Revenue (₱) | C9: Bookings | D9: Occupancy % | E9: RevPAR (₱) | F9: ADR (₱) | G9: MoM Growth | I9: Room Type | J9: Bookings | K9: Nights Sold | L9: Revenue (₱) | M9: Avg Rate (₱) | N9: % of Revenue
A10: Jan | B10: 185000 | C10: 4 | D10: 0.62 | E10: 3700 | F10: 46250 | G10: — | I10: Standard Room | J10: 12 | K10: 26 | L10: 287000 | M10: 11038 | N10: 0.059019495
A11: Feb | B11: 312000 | C11: 5 | D11: 0.75 | E11: 7548 | F11: 62400 | G11: =B11/B10-1 -> 0.68648649 | I11: Deluxe Room | J11: 16 | K11: 55 | L11: 698000 | M11: 12691 | N11: 0.1435387
A12: Mar | B12: 198000 | C12: 4 | D12: 0.58 | E12: 3705 | F12: 49500 | G12: =B12/B11-1 -> -0.36538462 | I12: Junior Suite | J12: 15 | K12: 42 | L12: 968000 | M12: 23048 | N12: 0.19906227
A13: Apr | B13: 285000 | C13: 5 | D13: 0.72 | E13: 6619 | F13: 57000 | G13: =B13/B12-1 -> 0.43939394 | I13: Executive Suite | J13: 10 | K13: 31 | L13: 938500 | M13: 30274 | N13: 0.1929958
A14: May | B14: 245000 | C14: 5 | D14: 0.68 | E14: 5374 | F14: 49000 | G14: =B14/B13-1 -> -0.14035088 | I14: Presidential Suite | J14: 8 | K14: 36 | L14: 1182000 | M14: 32833 | N14: 0.24306984
A15: Jun | B15: 310000 | C15: 5 | D15: 0.76 | E15: 7600 | F15: 62000 | G15: =B15/B14-1 -> 0.26530612 | I15: Family Room | J15: 8 | K15: 26 | L15: 385000 | M15: 14808 | N15: 0.079172493
A16: Jul | B16: 420000 | C16: 5 | D16: 0.85 | E16: 11516 | F16: 84000 | G16: =B16/B15-1 -> 0.35483871 | I16: Cottage | J16: 7 | K16: 21 | L16: 374000 | M16: 17810 | N16: 0.076910422
A17: Aug | B17: 395000 | C17: 5 | D17: 0.82 | E17: 10448 | F17: 79000 | G17: =B17/B16-1 -> -0.05952381 | I17: Glamping Tent | J17: 3 | K17: 9 | L17: 24000 | M17: 2667 | N17: 0.0049354281
A18: Sep | B18: 220000 | C18: 4 | D18: 0.6 | E18: 4258 | F18: 55000 | G18: =B18/B17-1 -> -0.44303797 | I18: Dormitory | J18: 1 | K18: 3 | L18: 6300 | M18: 2100 | N18: 0.0012955499
A19: Oct | B19: 380000 | C19: 5 | D19: 0.78 | E19: 9561 | F19: 76000 | G19: =B19/B18-1 -> 0.72727273
A20: Nov | B20: 295000 | C20: 4 | D20: 0.7 | E20: 6661 | F20: 73750 | G20: =B20/B19-1 -> -0.22368421
A21: Dec | B21: 597500 | C21: 8 | D21: 0.91 | E21: 17540 | F21: 74688 | G21: =B21/B20-1 -> 1.0254237
A22: TOTAL / AVG | B22: =SUM(B10:B21) -> 3842500 | C22: =SUM(C10:C21) -> 59 | D22: =AVERAGE(D10:D21) -> 0.73083333

Sheet Billing & Folio
A1: 💳 MARUYOG RIDGE — BILLING & FOLIO SUMMARY
A2: Guest Charges & Payment Tracking · All amounts in Philippine Peso (₱)
A3: Folio No. | B3: Booking ID | C3: Guest Name | D3: Room No. | E3: Room Charges (₱) | F3: F&B / Add-ons (₱) | G3: Discount (₱) | H3: VAT (12%) (₱) | I3: Grand Total (₱) | J3: Amount Paid (₱) | K3: Outstanding (₱)
A4: FL-2025-001 | B4: BK-2025-001 | C4: Reyes, Maria Clara | D4: 206 | E4: ='Booking Log'!K4 -> 19500 | F4: ='Booking Log'!L4 -> 4300 | G4: ='Booking Log'!M4 -> 500 | H4: =ROUND((E4+F4-G4)*0.12,2) -> 2796 | I4: ='Booking Log'!N4 -> 23300 | J4: ='Booking Log'!O4 -> 23300 | K4: =I4-J4 -> 0
A5: FL-2025-002 | B5: BK-2025-002 | C5: Cruz, Roberto | D5: 307 | E5: ='Booking Log'!K5 -> 72000 | F5: ='Booking Log'!L5 -> 0 | G5: ='Booking Log'!M5 -> 3000 | H5: =ROUND((E5+F5-G5)*0.12,2) -> 8280 | I5: ='Booking Log'!N5 -> 69000 | J5: ='Booking Log'!O5 -> 55200 | K5: =I5-J5 -> 13800
A6: FL-2025-003 | B6: BK-2025-003 | C6: Ramos, Eduardo | D6: 305 | E6: ='Booking Log'!K6 -> 31500 | F6: ='Booking Log'!L6 -> 1800 | G6: ='Booking Log'!M6 -> 0 | H6: =ROUND((E6+F6-G6)*0.12,2) -> 3996 | I6: ='Booking Log'!N6 -> 33300 | J6: ='Booking Log'!O6 -> 33300 | K6: =I6-J6 -> 0
A7: FL-2025-004 | B7: BK-2025-004 | C7: Santos, Jose Antonio | D7: 104 | E7: ='Booking Log'!K7 -> 5600 | F7: ='Booking Log'!L7 -> 0 | G7: ='Booking Log'!M7 -> 0 | H7: =ROUND((E7+F7-G7)*0.12,2) -> 672 | I7: ='Booking Log'!N7 -> 5600 | J7: ='Booking Log'!O7 -> 5600 | K7: =I7-J7 -> 0
A8: FL-2025-005 | B8: BK-2025-005 | C8: Smith, Robert James | D8: 203 | E8: ='Booking Log'!K8 -> 16000 | F8: ='Booking Log'!L8 -> 3000 | G8: ='Booking Log'!M8 -> 500 | H8: =ROUND((E8+F8-G8)*0.12,2) -> 2220 | I8: ='Booking Log'!N8 -> 18500 | J8: ='Booking Log'!O8 -> 0 | K8: =I8-J8 -> 18500
A9: FL-2025-006 | B9: BK-2025-006 | C9: Torres, Rico Paolo | D9: 207 | E9: ='Booking Log'!K9 -> 22500 | F9: ='Booking Log'!L9 -> 5000 | G9: ='Booking Log'!M9 -> 1000 | H9: =ROUND((E9+F9-G9)*0.12,2) -> 3180 | I9: ='Booking Log'!N9 -> 26500 | J9: ='Booking Log'!O9 -> 26500 | K9: =I9-J9 -> 0
A10: FL-2025-007 | B10: BK-2025-007 | C10: Domingo, Francis | D10: 307 | E10: ='Booking Log'!K10 -> 66000 | F10: ='Booking Log'!L10 -> 10000 | G10: ='Booking Log'!M10 -> 2000 | H10: =ROUND((E10+F10-G10)*0.12,2) -> 8880 | I10: ='Booking Log'!N10 -> 74000 | J10: ='Booking Log'!O10 -> 59200 | K10: =I10-J10 -> 14800
A11: FL-2025-008 | B11: BK-2025-008 | C11: Tan, Michelle | D11: 305 | E11: ='Booking Log'!K11 -> 24000 | F11: ='Booking Log'!L11 -> 5000 | G11: ='Booking Log'!M11 -> 2500 | H11: =ROUND((E11+F11-G11)*0.12,2) -> 3180 | I11: ='Booking Log'!N11 -> 26500 | J11: ='Booking Log'!O11 -> 26500 | K11: =I11-J11 -> 0
A12: FL-2025-009 | B12: BK-2025-009 | C12: Manalo, Benedict | D12: 206 | E12: ='Booking Log'!K12 -> 22500 | F12: ='Booking Log'!L12 -> 1800 | G12: ='Booking Log'!M12 -> 500 | H12: =ROUND((E12+F12-G12)*0.12,2) -> 2856 | I12: ='Booking Log'!N12 -> 23800 | J12: ='Booking Log'!O12 -> 23800 | K12: =I12-J12 -> 0
A13: FL-2025-010 | B13: BK-2025-010 | C13: Kim, Jisoo | D13: 302 | E13: ='Booking Log'!K13 -> 20800 | F13: ='Booking Log'!L13 -> 3000 | G13: ='Booking Log'!M13 -> 0 | H13: =ROUND((E13+F13-G13)*0.12,2) -> 2856 | I13: ='Booking Log'!N13 -> 23800 | J13: ='Booking Log'!O13 -> 0 | K13: =I13-J13 -> 23800
A14: FL-2025-011 | B14: BK-2025-011 | C14: Park, Seungri | D14: C01 | E14: ='Booking Log'!K14 -> 16500 | F14: ='Booking Log'!L14 -> 2500 | G14: ='Booking Log'!M14 -> 0 | H14: =ROUND((E14+F14-G14)*0.12,2) -> 2280 | I14: ='Booking Log'!N14 -> 19000 | J14: ='Booking Log'!O14 -> 9500 | K14: =I14-J14 -> 9500
A15: FL-2025-012 | B15: BK-2025-012 | C15: Garcia, Anna Marie | D15: 107 | E15: ='Booking Log'!K15 -> 13500 | F15: ='Booking Log'!L15 -> 5400 | G15: ='Booking Log'!M15 -> 800 | H15: =ROUND((E15+F15-G15)*0.12,2) -> 2172 | I15: ='Booking Log'!N15 -> 18100 | J15: ='Booking Log'!O15 -> 18100 | K15: =I15-J15 -> 0
... A83: FL-2026-020 | B83: BK-2026-020 | C83: Manalo, Benedict | D83: 307 | E83: ='Booking Log'!K83 -> 54000 | F83: ='Booking Log'!L83 -> 12000 | G83: ='Booking Log'!M83 -> 3000 | H83: =ROUND((E83+F83-G83)*0.12,2) -> 7560 | I83: ='Booking Log'!N83 -> 63000 | J83: ='Booking Log'!O83 -> 63000 | K83: =I83-J83 -> 0
